unified_focal_loss/__init__.py
unified_focal_loss/losses.py
unified_focal_loss_pytorch-0.1.2.dist-info/LICENSE
unified_focal_loss_pytorch-0.1.2.dist-info/METADATA
unified_focal_loss_pytorch-0.1.2.dist-info/WHEEL
unified_focal_loss_pytorch-0.1.2.dist-info/RECORD
